setup.py
Hoover.egg-info/PKG-INFO
Hoover.egg-info/SOURCES.txt
Hoover.egg-info/dependency_links.txt
Hoover.egg-info/requires.txt
Hoover.egg-info/top_level.txt
hoover/__init__.py
hoover/exceptions.py
hoover/handlers.py
hoover/input.py
hoover/session.py
hoover/utils.py
hoover/version.py