Metadata-Version: 1.0
Name: Hoover
Version: 0.6.0
Summary: Library for logging to Loggly from within Python webapps
Home-page: http://www.github.com/loggly/hoover
Author: Mike Blume
Author-email: mike@loggly.com
License: UNKNOWN
Platform: UNKNOWN
